langchain_core/__init__.py
langchain_core/agents.py
langchain_core/caches.py
langchain_core/chat_history.py
langchain_core/chat_loaders.py
langchain_core/chat_sessions.py
langchain_core/env.py
langchain_core/exceptions.py
langchain_core/globals.py
langchain_core/memory.py
langchain_core/prompt_values.py
langchain_core/py.typed
langchain_core/rate_limiters.py
langchain_core/retrievers.py
langchain_core/stores.py
langchain_core/structured_query.py
langchain_core/sys_info.py
langchain_core/_api/__init__.py
langchain_core/_api/beta_decorator.py
langchain_core/_api/deprecation.py
langchain_core/_api/internal.py
langchain_core/_api/path.py
langchain_core/beta/__init__.py
langchain_core/beta/runnables/__init__.py
langchain_core/beta/runnables/context.py
langchain_core/callbacks/__init__.py
langchain_core/callbacks/base.py
langchain_core/callbacks/file.py
langchain_core/callbacks/manager.py
langchain_core/callbacks/stdout.py
langchain_core/callbacks/streaming_stdout.py
langchain_core/document_loaders/__init__.py
langchain_core/document_loaders/base.py
langchain_core/document_loaders/blob_loaders.py
langchain_core/document_loaders/langsmith.py
langchain_core/documents/__init__.py
langchain_core/documents/base.py
langchain_core/documents/compressor.py
langchain_core/documents/transformers.py
langchain_core/embeddings/__init__.py
langchain_core/embeddings/embeddings.py
langchain_core/embeddings/fake.py
langchain_core/example_selectors/__init__.py
langchain_core/example_selectors/base.py
langchain_core/example_selectors/length_based.py
langchain_core/example_selectors/semantic_similarity.py
langchain_core/indexing/__init__.py
langchain_core/indexing/api.py
langchain_core/indexing/base.py
langchain_core/indexing/in_memory.py
langchain_core/language_models/__init__.py
langchain_core/language_models/base.py
langchain_core/language_models/chat_models.py
langchain_core/language_models/fake.py
langchain_core/language_models/fake_chat_models.py
langchain_core/language_models/llms.py
langchain_core_aipy-0.3.47.dist-info/METADATA
langchain_core_aipy-0.3.47.dist-info/WHEEL
langchain_core_aipy-0.3.47.dist-info/top_level.txt
langchain_core_aipy-0.3.47.dist-info/RECORD
